LICENSE
README.md
setup.py
MixedTypeANN/__init__.py
MixedTypeANN/approximate.py
MixedTypeANN/main.py
MixedTypeANN/type_enum.py
MixedTypeANN.egg-info/PKG-INFO
MixedTypeANN.egg-info/SOURCES.txt
MixedTypeANN.egg-info/dependency_links.txt
MixedTypeANN.egg-info/requires.txt
MixedTypeANN.egg-info/top_level.txt