Metadata-Version: 2.1
Name: MixedTypeANN
Version: 0.1.0
Summary: Approximate nearest neighbors for mixed type data
Author: Robin Chien
Author-email: goodnana1224@gmail.com
License: UNKNOWN
Keywords: nearest neighbor,knn,ANN
Platform: UNKNOWN
License-File: LICENSE
